configFileHelper/Config.py
configFileHelper/__init__.py
ConfigFileHelper-0.0.2.dist-info/LICENSE
ConfigFileHelper-0.0.2.dist-info/METADATA
ConfigFileHelper-0.0.2.dist-info/WHEEL
ConfigFileHelper-0.0.2.dist-info/top_level.txt
ConfigFileHelper-0.0.2.dist-info/RECORD
